/*    */ package com.alipay.config;
/*    */ 
/*    */ 
/*    */ 
/*    */ 
/*    */ 
/*    */ 
/*    */ 
/*    */ 
/*    */ 
/*    */ 
/*    */ 
/*    */ 
/*    */ 
/*    */ 
/*    */ 
/*    */ 
/*    */ 
/*    */ public class AlipayConfig
/*    */ {
/* 21 */   public static String app_id = "2016091200496126";
/*    */   
/*    */ 
/* 24 */   public static String merchant_private_key = "MIIEvQIBADANBgkqhkiG9w0BAQEFAASCBKcwggSjAgEAAoIBAQD4D4kVncOBiV5AedblD5xwl8AP8JyhWi+ZvHYyJBdCy7HYlbXYkGA5JArNgDEbx+MWSuiDqKP/bECt/CaX0lU4RW4nR4IwKTQPwaJA75QyzMWS7TM2CCUqSNRqCuNZ8Jl95KnWh4FalD0rYyYvL0HdhH1NbW66+D5SR8aO+MENH/g5SwjB9FbEMGtcOH6Lr4gOnkTQ4iZ3FalmBJRxISNjFORC8nIOw4D68+QLi4Rd9yRViuAEU3A0Dvm1STw5IK/+Sw7LcYBI9XJWoeNArSJ9CGOS6f0qFl70UQQzfXgEa8eLiHZr08NJdHbl6E47NpnC4Zdx3/jVy7XsJQodB6uBAgMBAAECggEAf6iHFM/G8GAAWFAbjnBVQwBlgA6EnOjrvENn1HAMZHytfte06MmMK3vn70/8dd6NeEh+llrwYx+TvbYZKmK9JqNch+xeDGj3+O/ej2p8KxSEzRMzGqhgb/1hC12lGQEgDNDjspqzsCi/vhddbET2sYhgb7tUk/XzJKb5gVR1DUoWMFw6j5wUe3C9Ll/XoOJyzYp4ALsbpZGXhW44e/ZGclb8Bt0k2LJBMVAdsJS1NCmwkRHxwkddNJpFySINJ0sDuTub98DeP7ZFZZ7MVMMyiInkrrM2CFYaeAFvaejD08d7nq6D+H6CESiX5r4/O1JNi2DTDeHNE3sHZ1MxmUYC0QKBgQD/MogRB6CSsUAXLQFOhKC0gGjh3biyYvl+2azbIEzPztX0qP7bpSJYX3OuEA35KOotQODk8Ak8Ndk8NevvHfjiuLPckkonURSP0waIgkhm2MwDit4MVhLrKd3Agrx/3oXOh+9qz2w6pQI17nvULhiE1TXmgwxQqdOmE5tuFImpBQKBgQD410IJ2OV0XRo88xHEYhiY+SOyZYhYYE7NASUiglXl/B3auLDwVjhf5CsnPoSRBb2h/qATn/GkiRZKWUUKTPwiZ0Yq50Uplbk9U3HOIrvn7uv2EMa/wowK0qvczuDpW57bCdnsO3rBgRfOfmbl5fhQKn1JuqL3EFTqZmGxQJSRTQKBgQCmriWLIfUx+s2GlaGV3DBu1LQsWjoJYXXd8WTiVo106X57Z2nWolv1ZprS5K+Lvrp9RjPdtB4EEpPJrNpl+qiVxNfNSEtgtKd+bPGGdbm+WvmdkrUHT6zZpiWtWHav+fJhfA3XMJVbFG2GNjbw1g6zq+KhpZSElvejMIlDc+yZ1QKBgAObazOlVz4mk1jK1TkZiu28vs25Nw7A5qOGHrmvVftteilPgBEbztlk/1MkTtujT6pnfH6MVP5jllUhkiSiFQ2SnavFinUd3H+NFBs+2aZ1CiqY96iT81+8ygz7WrtHPrhCHkyUWCUx79xobKlsefr/gq1s7SvTqsdzEHt3SjAJAoGAG4A1eCxbonjDUoa663Zx1Pweze5ivmhWDNa8/ojfoeVFARpJXDr2nQEFESVP5/g76C9MERfIU23yaiVeDYaHoJfq2pu9SuAyTwU4rir5PLZPcFPWBewLuP9P/7+XzxEqPu4fVyhM6kvMU+T8GODeRvo1z2r82JtH3Q+io+WH07g=";
/*    */   
/*    */ 
/* 27 */   public static String alipay_public_key = "MIIBIjANBgkqhkiG9w0BAQEFAAOCAQ8AMIIBCgKCAQEA+A+JFZ3DgYleQHnW5Q+ccJfAD/CcoVovmbx2MiQXQsux2JW12JBgOSQKzYAxG8fjFkrog6ij/2xArfwml9JVOEVuJ0eCMCk0D8GiQO+UMszFku0zNgglKkjUagrjWfCZfeSp1oeBWpQ9K2MmLy9B3YR9TW1uuvg+UkfGjvjBDR/4OUsIwfRWxDBrXDh+i6+IDp5E0OImdxWpZgSUcSEjYxTkQvJyDsOA+vPkC4uEXfckVYrgBFNwNA75tUk8OSCv/ksOy3GASPVyVqHjQK0ifQhjkun9KhZe9FEEM314BGvHi4h2a9PDSXR25ehOOzaZwuGXcd/41cu17CUKHQergQIDAQAB";
/*    */   
/*    */ 
/* 30 */   public static String notify_url = "http://localhost:8080/LGG/notify_url.jsp";
/*    */   
/*    */ 
/* 33 */   public static String return_url = "http://localhost:8080/LGG/return_url.jsp";
/*    */   
/*    */ 
/* 36 */   public static String sign_type = "RSA2";
/*    */   
/*    */ 
/* 39 */   public static String charset = "utf-8";
/*    */   
/*    */ 
/* 42 */   public static String gatewayUrl = "https://openapi.alipaydev.com/gateway.do";
/*    */   
/*    */ 
/* 45 */   public static String log_path = "C:\\";
/*    */   
/*    */   /* Error */
/*    */   public static void logResult(String sWord)
/*    */   {
/*    */     // Byte code:
/*    */     //   0: aconst_null
/*    */     //   1: astore_1
/*    */     //   2: new 63	java/io/FileWriter
/*    */     //   5: dup
/*    */     //   6: new 65	java/lang/StringBuilder
/*    */     //   9: dup
/*    */     //   10: getstatic 52	com/alipay/config/AlipayConfig:log_path	Ljava/lang/String;
/*    */     //   13: invokestatic 67	java/lang/String:valueOf	(Ljava/lang/Object;)Ljava/lang/String;
/*    */     //   16: invokespecial 73	java/lang/StringBuilder:<init>	(Ljava/lang/String;)V
/*    */     //   19: ldc 75
/*    */     //   21: invokevirtual 77	java/lang/StringBuilder:append	(Ljava/lang/String;)Ljava/lang/StringBuilder;
/*    */     //   24: invokestatic 81	java/lang/System:currentTimeMillis	()J
/*    */     //   27: invokevirtual 87	java/lang/StringBuilder:append	(J)Ljava/lang/StringBuilder;
/*    */     //   30: ldc 90
/*    */     //   32: invokevirtual 77	java/lang/StringBuilder:append	(Ljava/lang/String;)Ljava/lang/StringBuilder;
/*    */     //   35: invokevirtual 92	java/lang/StringBuilder:toString	()Ljava/lang/String;
/*    */     //   38: invokespecial 96	java/io/FileWriter:<init>	(Ljava/lang/String;)V
/*    */     //   41: astore_1
/*    */     //   42: aload_1
/*    */     //   43: aload_0
/*    */     //   44: invokevirtual 97	java/io/FileWriter:write	(Ljava/lang/String;)V
/*    */     //   47: goto +50 -> 97
/*    */     //   50: astore_2
/*    */     //   51: aload_2
/*    */     //   52: invokevirtual 100	java/lang/Exception:printStackTrace	()V
/*    */     //   55: aload_1
/*    */     //   56: ifnull +59 -> 115
/*    */     //   59: aload_1
/*    */     //   60: invokevirtual 105	java/io/FileWriter:close	()V
/*    */     //   63: goto +52 -> 115
/*    */     //   66: astore 4
/*    */     //   68: aload 4
/*    */     //   70: invokevirtual 108	java/io/IOException:printStackTrace	()V
/*    */     //   73: goto +42 -> 115
/*    */     //   76: astore_3
/*    */     //   77: aload_1
/*    */     //   78: ifnull +17 -> 95
/*    */     //   81: aload_1
/*    */     //   82: invokevirtual 105	java/io/FileWriter:close	()V
/*    */     //   85: goto +10 -> 95
/*    */     //   88: astore 4
/*    */     //   90: aload 4
/*    */     //   92: invokevirtual 108	java/io/IOException:printStackTrace	()V
/*    */     //   95: aload_3
/*    */     //   96: athrow
/*    */     //   97: aload_1
/*    */     //   98: ifnull +17 -> 115
/*    */     //   101: aload_1
/*    */     //   102: invokevirtual 105	java/io/FileWriter:close	()V
/*    */     //   105: goto +10 -> 115
/*    */     //   108: astore 4
/*    */     //   110: aload 4
/*    */     //   112: invokevirtual 108	java/io/IOException:printStackTrace	()V
/*    */     //   115: return
/*    */     // Line number table:
/*    */     //   Java source line #55	-> byte code offset #0
/*    */     //   Java source line #57	-> byte code offset #2
/*    */     //   Java source line #58	-> byte code offset #42
/*    */     //   Java source line #59	-> byte code offset #47
/*    */     //   Java source line #60	-> byte code offset #51
/*    */     //   Java source line #62	-> byte code offset #55
/*    */     //   Java source line #64	-> byte code offset #59
/*    */     //   Java source line #65	-> byte code offset #63
/*    */     //   Java source line #66	-> byte code offset #68
/*    */     //   Java source line #61	-> byte code offset #76
/*    */     //   Java source line #62	-> byte code offset #77
/*    */     //   Java source line #64	-> byte code offset #81
/*    */     //   Java source line #65	-> byte code offset #85
/*    */     //   Java source line #66	-> byte code offset #90
/*    */     //   Java source line #69	-> byte code offset #95
/*    */     //   Java source line #62	-> byte code offset #97
/*    */     //   Java source line #64	-> byte code offset #101
/*    */     //   Java source line #65	-> byte code offset #105
/*    */     //   Java source line #66	-> byte code offset #110
/*    */     //   Java source line #70	-> byte code offset #115
/*    */     // Local variable table:
/*    */     //   start	length	slot	name	signature
/*    */     //   0	116	0	sWord	String
/*    */     //   1	101	1	writer	java.io.FileWriter
/*    */     //   50	2	2	e	Exception
/*    */     //   76	20	3	localObject	Object
/*    */     //   66	3	4	e	java.io.IOException
/*    */     //   88	3	4	e	java.io.IOException
/*    */     //   108	3	4	e	java.io.IOException
/*    */     // Exception table:
/*    */     //   from	to	target	type
/*    */     //   2	47	50	java/lang/Exception
/*    */     //   59	63	66	java/io/IOException
/*    */     //   2	55	76	finally
/*    */     //   81	85	88	java/io/IOException
/*    */     //   101	105	108	java/io/IOException
/*    */   }
/*    */ }


/* Location:              F:\jiang\WEB-INF\classes\!\com\alipay\config\AlipayConfig.class
 * Java compiler version: 8 (52.0)
 * JD-Core Version:       0.7.1
 */